pyPM5/__init__.py
pyPM5/pyPM5.py
pyPM5-0.0.3.dist-info/METADATA
pyPM5-0.0.3.dist-info/WHEEL
pyPM5-0.0.3.dist-info/top_level.txt
pyPM5-0.0.3.dist-info/RECORD
