Metadata-Version: 2.1
Name: pyPM5
Version: 0.0.3
Summary: Package to interface Virginia Diodes PM5 Powermeter with Python
Author: Matt Jamieson
Author-email: <mjamieson21@outlook.com>
Keywords: python,terahertz,powermeter,PM5,Virginia Diodes
Classifier: Development Status :: 3 - Alpha
Classifier: Programming Language :: Python :: 3
Classifier: Operating System :: Microsoft :: Windows
Requires-Dist: pyvisa
